arseparse.py
arseparse-0.1.2.dist-info/DESCRIPTION.rst
arseparse-0.1.2.dist-info/METADATA
arseparse-0.1.2.dist-info/RECORD
arseparse-0.1.2.dist-info/WHEEL
arseparse-0.1.2.dist-info/metadata.json
arseparse-0.1.2.dist-info/top_level.txt
