Metadata-Version: 2.0
Name: arseparse
Version: 0.1.2
Summary: Command-line app helper library
Home-page: https://github.com/sgarcez/arseparse
Author: Sergio Garcez
Author-email: garcez.sergio@gmail.com
License: MIT
Keywords: cli,argparse,command-line
Platform: UNKNOWN
Classifier: Development Status :: 4 - Beta
Classifier: Intended Audience :: Developers
Classifier: License :: OSI Approved :: MIT License
Classifier: Operating System :: OS Independent
Classifier: Programming Language :: Python
Classifier: Programming Language :: Python :: 2
Classifier: Programming Language :: Python :: 2.7
Classifier: Programming Language :: Python :: 3
Classifier: Programming Language :: Python :: 3.6
Classifier: Topic :: Software Development :: Libraries :: Python Modules
